pybacktestchain_EV/.DS_Store
pybacktestchain_EV/__init__.py
pybacktestchain_EV/blockchain.py
pybacktestchain_EV/broker.py
pybacktestchain_EV/data_module.py
pybacktestchain_EV/pybacktestchain.py
pybacktestchain_EV/risk_metrics.py
pybacktestchain_EV/strategies.py
pybacktestchain_EV/utils.py
pybacktestchain_ev-0.1.2.dist-info/LICENSE
pybacktestchain_ev-0.1.2.dist-info/METADATA
pybacktestchain_ev-0.1.2.dist-info/WHEEL
pybacktestchain_ev-0.1.2.dist-info/RECORD
