Metadata-Version: 2.3
Name: pybacktestchain_ev
Version: 0.1.2
Summary: Improved pybacktestchain library with interactive UI and features added (risk measures, trading strategies, multiple asset classes)
License: MIT
Author: Enzo Volpato
Author-email: enzo.volpato@outlook.fr
Requires-Python: >=3.10,<4
Classifier: License :: OSI Approved :: MIT License
Classifier: Programming Language :: Python :: 3
Classifier: Programming Language :: Python :: 3.10
Classifier: Programming Language :: Python :: 3.11
Classifier: Programming Language :: Python :: 3.12
Classifier: Programming Language :: Python :: 3.13
Requires-Dist: markdown-it-py (>=1.0.0,<3.0.0)
Requires-Dist: matplotlib (>=3.5,<4.0)
Requires-Dist: numpy (>=1.22,<2.0)
Requires-Dist: pandas (>=2.2.2,<3.0.0)
Requires-Dist: pytest (>=7.0,<8.0)
Requires-Dist: scipy (>=1.7.0,<1.14.0)
Requires-Dist: seaborn (>=0.11,<0.12)
Requires-Dist: sec-cik-mapper (==2.1.0)
Requires-Dist: streamlit (>=1.0,<2.0)
Requires-Dist: yfinance (>=0.2.41,<0.3.0)
